COPYING
MANIFEST.in
NEWS.txt
README.txt
distribute_setup.py
setup.cfg
setup.py
setup_helpers.py
apesmit/__init__.py
apesmit_py2.egg-info/PKG-INFO
apesmit_py2.egg-info/SOURCES.txt
apesmit_py2.egg-info/dependency_links.txt
apesmit_py2.egg-info/top_level.txt
test/test.py